odoo8_addon_l10n_pe_add_series_field-8.0.1.0.0-py2.7-nspkg.pth
odoo_addons/l10n_pe_add_series_field/__openerp__.py
odoo_addons/l10n_pe_add_series_field/__init__.py
odoo_addons/l10n_pe_add_series_field/README.rst
odoo_addons/l10n_pe_add_series_field/view/account_journal_view.xml
odoo_addons/l10n_pe_add_series_field/i18n/es.po
odoo_addons/l10n_pe_add_series_field/i18n/es_PE.po
odoo_addons/l10n_pe_add_series_field/model/__init__.py
odoo_addons/l10n_pe_add_series_field/model/journal.py
odoo8_addon_l10n_pe_add_series_field-8.0.1.0.0.dist-info/top_level.txt
odoo8_addon_l10n_pe_add_series_field-8.0.1.0.0.dist-info/WHEEL
odoo8_addon_l10n_pe_add_series_field-8.0.1.0.0.dist-info/RECORD
odoo8_addon_l10n_pe_add_series_field-8.0.1.0.0.dist-info/metadata.json
odoo8_addon_l10n_pe_add_series_field-8.0.1.0.0.dist-info/DESCRIPTION.rst
odoo8_addon_l10n_pe_add_series_field-8.0.1.0.0.dist-info/METADATA
odoo8_addon_l10n_pe_add_series_field-8.0.1.0.0.dist-info/namespace_packages.txt
